{
  "race_id": 22730,
  "test_data": "false",
  "year": 2023,
  "state_fips": "55",
  "state_name": "Wisconsin",
  "state": "WI",
  "ecvotes": null,
  "election_type_id": 1,
  "name": "General Election",
  "race_date": "2023-04-04",
  "office_id": 25,
  "office": "Stevens Point Common Council",
  "district": "1",
  "party_id": 242,
  "party": "Nonpartisan",
  "level": "Universal",
  "advance_candidates": "false",
  "last_updated": "2023-04-05T05:34:12.315Z",
  "race_created": "2023-03-21T14:25:15.206Z",
  "poll_close_time": "2023-04-04T21:00:00.000Z",
  "marquee_race": "false",
  "abev_expected": "false",
  "topline_results": {
    "votes": {
      "48861": 382,
      "48862": 211
    },
    "voting_data": {
      "48861": {
        "absentee_ballots_early_votes": 0,
        "election_day_votes": 0
      },
      "48862": {
        "absentee_ballots_early_votes": 0,
        "election_day_votes": 0
      }
    },
    "estimated_votes": {
      "estimated_votes_low": 0,
      "estimated_votes_mid": 0,
      "estimated_votes_high": 0
    },
    "precincts": {
      "total": 1,
      "reporting": 1
    },
    "called_candidates": [],
    "call_times": [],
    "advancing_candidates": [],
    "advance_times": []
  },
  "counties": [
    {
      "id": 3205,
      "county": "Portage",
      "fips": "55097",
      "estimated_votes": {
        "estimated_votes_low": 0,
        "estimated_votes_mid": 0,
        "estimated_votes_high": 0
      },
      "precincts": {
        "total": 1,
        "reporting": 1
      },
      "votes": {
        "48861": 382,
        "48862": 211
      },
      "voting_data": {
        "48861": {
          "absentee_ballots_early_votes": 0,
          "election_day_votes": 0
        },
        "48862": {
          "absentee_ballots_early_votes": 0,
          "election_day_votes": 0
        }
      },
      "vcus": [
        {
          "id": 709,
          "vcu": "Portage",
          "fips": "55097",
          "estimated_votes": {
            "estimated_votes_low": 0,
            "estimated_votes_mid": 0,
            "estimated_votes_high": 0
          },
          "precincts": {
            "total": 1,
            "reporting": 1
          },
          "votes": {
            "48861": 382,
            "48862": 211
          },
          "voting_data": {
            "48861": {
              "absentee_ballots_early_votes": 0,
              "election_day_votes": 0
            },
            "48862": {
              "absentee_ballots_early_votes": 0,
              "election_day_votes": 0
            }
          }
        }
      ]
    }
  ],
  "candidates": [
    {
      "cand_id": 48861,
      "party_name": "Nonpartisan",
      "party_id": 242,
      "first_name": "Marc",
      "last_name": "Christianson",
      "incumbent": true
    },
    {
      "cand_id": 48862,
      "party_name": "Nonpartisan",
      "party_id": 242,
      "first_name": "Gracia",
      "last_name": "Day",
      "incumbent": false
    }
  ]
}